llm_cost_monitor/__init__.py
llm_cost_monitor/api_client.py
llm_cost_monitor/api_response.py
llm_cost_monitor/configuration.py
llm_cost_monitor/exceptions.py
llm_cost_monitor/py.typed
llm_cost_monitor/rest.py
llm_cost_monitor/api/__init__.py
llm_cost_monitor/api/alerts_api.py
llm_cost_monitor/api/events_api.py
llm_cost_monitor/api/metrics_api.py
llm_cost_monitor/api/pricing_api.py
llm_cost_monitor/models/__init__.py
llm_cost_monitor/models/alert.py
llm_cost_monitor/models/cost_breakdown.py
llm_cost_monitor/models/create_alert_request.py
llm_cost_monitor/models/create_event_request.py
llm_cost_monitor/models/error_response.py
llm_cost_monitor/models/error_response_error.py
llm_cost_monitor/models/event.py
llm_cost_monitor/models/event_list_response.py
llm_cost_monitor/models/event_response.py
llm_cost_monitor/models/metric_point.py
llm_cost_monitor/models/metrics_response.py
llm_cost_monitor/models/model_pricing.py
llm_cost_monitor/models/pagination_meta.py
llm_cost_monitor/models/usage_record.py
llm_cost_monitor/models/usage_summary.py
llm_cost_monitor-1.1.0.dist-info/METADATA
llm_cost_monitor-1.1.0.dist-info/WHEEL
llm_cost_monitor-1.1.0.dist-info/top_level.txt
llm_cost_monitor-1.1.0.dist-info/RECORD
