Metadata-Version: 2.4
Name: llm-cost-monitor
Version: 1.1.0
Summary: Python SDK for LLM Cost Monitor - Track, aggregate, and analyze LLM usage costs
Home-page: 
Author: OpenAPI Generator community
Author-email: LLM Cost Monitor <team@llmcostmonitor.dev>
License: MIT
Project-URL: Repository, https://github.com/check-ai/llm-cost-monitor
Keywords: llm,openai,anthropic,cost,monitoring,observability,gpt-4,claude
Requires-Python: >=3.9
Requires-Dist: urllib3<3.0.0,>=2.1.0
Requires-Dist: python-dateutil>=2.8.2
Requires-Dist: pydantic>=2
Requires-Dist: typing-extensions>=4.7.1
Dynamic: author
